SCLibrary/__init__.py
SCLibrary/base/__init__.py
SCLibrary/base/hook.py
SCLibrary/base/robotlibcore.py
SCLibrary/builtin/__init__.py
SCLibrary/builtin/db.py
SCLibrary/builtin/env.py
SCLibrary/builtin/locust.py
SCLibrary/builtin/loglistener.py
SCLibrary/builtin/randomkeywords.py
SCLibrary/builtin/requester.py
SCLibrary/builtin/select.py
SCLibrary/builtin/util.py
SCLibrary/builtin/websql/__init__.py
SCLibrary/builtin/websql/crpt.py
SCLibrary/builtin/websql/shitf_linux.so
SCLibrary/builtin/websql/shitf_mac.so
SCLibrary/builtin/websql/websql.py
SCLibrary/fork_requests/RequestsKeywords.py
SCLibrary/fork_requests/__init__.py
SCLibrary/fork_requests/compat.py
SCLibrary/fork_requests/version.py
SCLibrary/zk/__init__.py
SCLibrary/zk/registry.py
rf_sclibrary-1.3.4.dist-info/METADATA
rf_sclibrary-1.3.4.dist-info/RECORD
rf_sclibrary-1.3.4.dist-info/WHEEL
rf_sclibrary-1.3.4.dist-info/top_level.txt
