Metadata-Version: 2.1
Name: rf-sclibrary
Version: 1.3.4
Summary: SC utility library for Robot Framework
Home-page: https://github.com/
Author: YoKey
Author-email: yokeyword@gmail.com
License: UNKNOWN
Platform: UNKNOWN
Requires-Dist: astroid (==2.1.0)
Requires-Dist: atomicwrites (==1.2.1)
Requires-Dist: attrs (==18.2.0)
Requires-Dist: bleach (==3.1.0)
Requires-Dist: certifi (==2018.11.29)
Requires-Dist: chardet (==3.0.4)
Requires-Dist: docutils (==0.14)
Requires-Dist: enum34 (==1.1.6)
Requires-Dist: idna (==2.8)
Requires-Dist: isort (==4.3.4)
Requires-Dist: kazoo (==2.6.0)
Requires-Dist: lazy-object-proxy (==1.3.1)
Requires-Dist: lxml (==4.2.5)
Requires-Dist: mccabe (==0.6.1)
Requires-Dist: more-itertools (==5.0.0)
Requires-Dist: namedlist (==1.7)
Requires-Dist: pkginfo (==1.5.0.1)
Requires-Dist: pluggy (==0.8.0)
Requires-Dist: psycopg2-binary (==2.7.7)
Requires-Dist: py (==1.7.0)
Requires-Dist: Pygments (==2.3.1)
Requires-Dist: pylint (==2.2.2)
Requires-Dist: PyMySQL (==0.9.3)
Requires-Dist: readme-renderer (==24.0)
Requires-Dist: requests (==2.21.0)
Requires-Dist: requests-toolbelt (==0.8.0)
Requires-Dist: robotframework-databaselibrary (==1.2)
Requires-Dist: doraemon-robotframework (==1.5.0)
Requires-Dist: six (==1.11.0)
Requires-Dist: tqdm (==4.29.1)
Requires-Dist: urllib3 (==1.24.1)
Requires-Dist: webencodings (==0.5.1)
Requires-Dist: wrapt (==1.10.11)
Requires-Dist: locustio (==0.9.0)
Requires-Dist: pyyaml (==4.2b4)
Requires-Dist: autopep8 (==1.4.4)
